README.rst
plugin_template.py
setup.cfg
setup.py
kupfer_plugin_name.egg-info/PKG-INFO
kupfer_plugin_name.egg-info/SOURCES.txt
kupfer_plugin_name.egg-info/dependency_links.txt
kupfer_plugin_name.egg-info/not-zip-safe
kupfer_plugin_name.egg-info/top_level.txt